CHANGELOG.rst
MANIFEST.in
README.rst
setup.py
downyt/__init__.py
downyt/cli.py
downyt.egg-info/PKG-INFO
downyt.egg-info/SOURCES.txt
downyt.egg-info/dependency_links.txt
downyt.egg-info/entry_points.txt
downyt.egg-info/not-zip-safe
downyt.egg-info/requires.txt
downyt.egg-info/top_level.txt