Metadata-Version: 1.1
Name: downyt
Version: 0.1.1
Summary: Download youtube videos of different filetypes.
Home-page: https://github.com/elbaschid/downyt
Author: Sebastian Vetter
Author-email: sebastian@roadside-developer.com
License: MIT
Keywords: video,download,youtube
Platform: UNKNOWN
Classifier: Development Status :: 3 - Alpha
Classifier: Intended Audience :: Developers
Classifier: License :: OSI Approved :: MIT License
Classifier: Natural Language :: English
Classifier: Programming Language :: Python :: 3
Classifier: Programming Language :: Python :: 3.3
